[
  {
    "url": "https://unhealthy-obsession.proffer.dev/",
    "title": "unhealthy-obsession.proffer.dev"
  },
  {
    "url": "https://weyland-yutani.proffer.dev/",
    "title": "weyland-yutani.proffer.dev"
  },
  {
    "url": "https://tickets.proffer.dev/",
    "title": "tickets.proffer.dev"
  },
  {
    "url": "https://aan-news.proffer.dev/",
    "title": "aan-news.proffer.dev"
  },
  {
    "url": "https://whatisjacobplaying.com/",
    "title": "whatisjacobplaying.com"
  },
  {
    "url": "https://firstredsquadron.com/",
    "title": "firstredsquadron.com"
  }
]
